{"openapi":"3.0.0","paths":{"/v1/api/user/all":{"get":{"operationId":"UsersController_findUsers","summary":"Get all users","parameters":[],"responses":{"200":{"description":"Return all users","content":{"application/json":{"schema":{"type":"array","items":{"$ref":"#/components/schemas/User"}}}}}},"tags":["User"],"security":[{"bearer":[]}]}},"/v1/api/user/{id}":{"get":{"operationId":"UsersController_findUser","summary":"Find user by id","parameters":[{"name":"id","required":true,"in":"path","schema":{"type":"number"}}],"responses":{"200":{"description":"Return  user","content":{"application/json":{"schema":{"$ref":"#/components/schemas/User"}}}}},"tags":["User"],"security":[{"bearer":[]}]}},"/v1/api/user":{"get":{"operationId":"UsersController_getCurrent","summary":"Get current user","parameters":[],"responses":{"200":{"description":"Return  user","content":{"application/json":{"schema":{"$ref":"#/components/schemas/User"}}}}},"tags":["User"],"security":[{"bearer":[]}]}},"/v1/api/user/update":{"patch":{"operationId":"UsersController_updateUserById","summary":"Update current user","parameters":[],"requestBody":{"required":true,"content":{"application/json":{"schema":{"$ref":"#/components/schemas/UpdateUserDto"}}}},"responses":{"200":{"description":"Return  user","content":{"application/json":{"schema":{"$ref":"#/components/schemas/User"}}}}},"tags":["User"],"security":[{"bearer":[]}]}},"/v1/api/user/delete":{"delete":{"operationId":"UsersController_deleteUser","summary":"Delete current user","parameters":[],"responses":{"200":{"description":"Return  user","content":{"application/json":{"schema":{"$ref":"#/components/schemas/User"}}}}},"tags":["User"],"security":[{"bearer":[]}]}},"/v1/api/profile":{"post":{"operationId":"UsersController_createUserProfile","summary":"create current user profile","parameters":[],"requestBody":{"required":true,"content":{"application/json":{"schema":{"$ref":"#/components/schemas/CreateProfileDto"}}}},"responses":{"200":{"description":"Create User Profile","content":{"application/json":{"schema":{"$ref":"#/components/schemas/Profile"}}}}},"tags":["User"],"security":[{"bearer":[]}]},"get":{"operationId":"UsersController_getUserProfile","summary":"Get current user profile","parameters":[],"responses":{"200":{"description":"Return  User Profile","content":{"application/json":{"schema":{"$ref":"#/components/schemas/Profile"}}}}},"tags":["User"],"security":[{"bearer":[]}]}},"/v1/api/auth/register":{"post":{"operationId":"AuthController_createUser","summary":"Register user","parameters":[],"requestBody":{"required":true,"content":{"application/json":{"schema":{"$ref":"#/components/schemas/AuthDto"}}}},"responses":{"201":{"description":""}},"tags":["Authentication"]}},"/v1/api/auth/login":{"post":{"operationId":"AuthController_login","summary":"Login","parameters":[],"requestBody":{"required":true,"content":{"application/json":{"schema":{"$ref":"#/components/schemas/AuthDto"}}}},"responses":{"200":{"description":"Return  token"}},"tags":["Authentication"]}},"/v1/api/auth/refresh":{"post":{"operationId":"AuthController_refreshToken","summary":"Refresh token","parameters":[],"requestBody":{"required":true,"content":{"application/json":{"schema":{"type":"string"}}}},"responses":{"200":{"description":"Return  token"}},"tags":["Authentication"],"security":[{"bearer":[]}]}},"/v1/api/auth/logout":{"post":{"operationId":"AuthController_logout","summary":"Logout","parameters":[],"responses":{"201":{"description":""}},"tags":["Authentication"],"security":[{"bearer":[]}]}},"/v1/api/todo/all":{"get":{"operationId":"TodoController_findAll","summary":"Get all todos","parameters":[],"responses":{"200":{"description":"Return all users","content":{"application/json":{"schema":{"type":"array","items":{"$ref":"#/components/schemas/Todo"}}}}}},"tags":["Todo"],"security":[{"bearer":[]}]}},"/v1/api/todo/create":{"post":{"operationId":"TodoController_create","summary":"Create new Todo","parameters":[],"requestBody":{"required":true,"content":{"application/json":{"schema":{"$ref":"#/components/schemas/TodoDto"}}}},"responses":{"200":{"description":"Create  userProfile","content":{"application/json":{"schema":{"$ref":"#/components/schemas/Todo"}}}}},"tags":["Todo"],"security":[{"bearer":[]}]}},"/v1/api/todo/{id}":{"get":{"operationId":"TodoController_findUser","summary":"Find todo by id","parameters":[{"name":"id","required":true,"in":"path","schema":{"type":"number"}}],"responses":{"200":{"description":"Return  todo","content":{"application/json":{"schema":{"$ref":"#/components/schemas/Todo"}}}}},"tags":["Todo"],"security":[{"bearer":[]}]},"patch":{"operationId":"TodoController_updateById","summary":"Update todo by id","parameters":[{"name":"id","required":true,"in":"path","schema":{"type":"number"}}],"requestBody":{"required":true,"content":{"application/json":{"schema":{"$ref":"#/components/schemas/TodoDto"}}}},"responses":{"200":{"description":"Return  todo","content":{"application/json":{"schema":{"$ref":"#/components/schemas/Todo"}}}}},"tags":["Todo"],"security":[{"bearer":[]}]}}},"info":{"title":"Snakes Pool","description":"How to treat with snakes ?","version":"1.0","contact":{}},"tags":[],"servers":[],"components":{"schemas":{"Profile":{"type":"object","properties":{"id":{"type":"number"},"firstName":{"type":"string"},"lastName":{"type":"string"},"mobileNumber":{"type":"string"},"email":{"type":"string"},"birthDate":{"type":"string","format":"date-time"},"createdAt":{"type":"string","format":"date-time"}},"required":["id","firstName","lastName","mobileNumber","email","birthDate","createdAt"]},"Task":{"type":"object","properties":{"id":{"type":"number","format":"number"},"title":{"type":"string","example":"title","description":"Task title"},"description":{"type":"string","example":"description","description":"Task description"},"done":{"type":"boolean"},"deleted":{"type":"boolean"},"createdAt":{"type":"string","format":"date-time"},"updatedAt":{"type":"string","format":"date-time"},"todo":{"$ref":"#/components/schemas/Todo"}},"required":["id","title","description","done","deleted","createdAt","updatedAt","todo"]},"Todo":{"type":"object","properties":{"id":{"type":"number","format":"number"},"title":{"type":"string","example":"title","description":"Todo title"},"description":{"type":"string","example":"description","description":"Todo description"},"done":{"type":"boolean"},"deleted":{"type":"boolean"},"createdAt":{"type":"string","format":"date-time"},"updatedAt":{"type":"string","format":"date-time"},"dueDate":{"type":"string","format":"date-time"},"reminderDate":{"type":"string","format":"date-time"},"repeat":{"type":"string","format":"date-time"},"repeatTime":{"type":"string","enum":[5,10,15,30,60,"daily","weekly","monthly","yearly","none"],"default":"none","example":"daily"},"tasks":{"format":"table","allOf":[{"$ref":"#/components/schemas/Task"}]}},"required":["id","title","description","done","deleted","createdAt","updatedAt","dueDate","reminderDate","repeat","repeatTime","tasks"]},"User":{"type":"object","properties":{"id":{"type":"number","format":"number"},"username":{"type":"string"},"password":{"type":"string","example":"password","description":"The user password"},"refreshToken":{"type":"string"},"createdAt":{"type":"string","format":"date-time"},"updatedAt":{"type":"string","format":"date-time"},"profile":{"format":"profile","allOf":[{"$ref":"#/components/schemas/Profile"}]},"todos":{"format":"table","allOf":[{"$ref":"#/components/schemas/Todo"}]}},"required":["id","username","password","refreshToken","createdAt","updatedAt","profile","todos"]},"UpdateUserDto":{"type":"object","properties":{"username":{"type":"string","format":"string"},"password":{"type":"string","format":"string"}},"required":["username","password"]},"CreateProfileDto":{"type":"object","properties":{"firstName":{"type":"string","format":"string"},"lastName":{"type":"string","format":"string"},"email":{"type":"string","format":"email"},"mobileNumber":{"type":"string","format":"mobile"},"birthDate":{"type":"string","format":"date-time"}},"required":["firstName","lastName","email","mobileNumber","birthDate"]},"AuthDto":{"type":"object","properties":{"username":{"type":"string","format":"string"},"password":{"type":"string","format":"string"}},"required":["username","password"]},"TodoDto":{"type":"object","properties":{"title":{"type":"string"},"description":{"type":"string"},"done":{"type":"boolean","format":"true,false","default":false},"deleted":{"type":"boolean","format":"true,false","default":false},"repeat":{"type":"boolean","format":"true,false","default":false},"user":{"format":"user","allOf":[{"$ref":"#/components/schemas/User"}]},"repeatTime":{"type":"string","enum":[5,10,15,30,60,"daily","weekly","monthly","yearly","none"],"example":"daily"},"dueDate":{"type":"string","format":"date-time"},"reminderDate":{"type":"string","format":"date-time"}},"required":["title","description","done","deleted","repeat","user","repeatTime","dueDate","reminderDate"]}}}}